filter_persist/__init__.py
filter_persist/example.py
filter_persist/frontend/build/asset-manifest.json
filter_persist/frontend/build/bootstrap.min.css
filter_persist/frontend/build/index.html
filter_persist/frontend/build/static/css/main.265676ba.css
filter_persist/frontend/build/static/css/main.5fcca8da.css
filter_persist/frontend/build/static/css/main.5fcca8da.css.map
filter_persist/frontend/build/static/js/main.7c582e62.js
filter_persist/frontend/build/static/js/main.7c582e62.js.LICENSE.txt
filter_persist/frontend/build/static/js/main.7c582e62.js.map
filter_persist/frontend/build/static/js/main.c34c89af.js
filter_persist/frontend/build/static/js/main.c34c89af.js.LICENSE.txt
filter_persist/frontend/build/static/js/main.fdea2fca.js
filter_persist/frontend/build/static/js/main.fdea2fca.js.LICENSE.txt
filter_persist/frontend/build/static/js/main.fdea2fca.js.map
filter_persist-0.2.0.dist-info/METADATA
filter_persist-0.2.0.dist-info/WHEEL
filter_persist-0.2.0.dist-info/top_level.txt
filter_persist-0.2.0.dist-info/RECORD
