Metadata-Version: 2.4
Name: filter-persist
Version: 0.2.0
Summary: Custom Streamlit AgGrid component with 0.1.5 and greater having major grid options
Author: Parshav Shivnani
Classifier: Programming Language :: Python :: 3
Classifier: Operating System :: OS Independent
Requires-Dist: streamlit>=1.0
Dynamic: author
Dynamic: classifier
Dynamic: description
Dynamic: description-content-type
Dynamic: requires-dist
Dynamic: summary
